mohaf/__init__.py
mohaf/auction_mechanisms.py
mohaf/cli.py
mohaf/core.py
mohaf/scenarios.py
mohaf/utils.py
mohaf-0.2.0.dist-info/licenses/LICENSE
mohaf-0.2.0.dist-info/METADATA
mohaf-0.2.0.dist-info/WHEEL
mohaf-0.2.0.dist-info/entry_points.txt
mohaf-0.2.0.dist-info/top_level.txt
mohaf-0.2.0.dist-info/RECORD
