Metadata-Version: 2.4
Name: mohaf
Version: 0.2.0
Summary: A research framework for Multi-Objective Hierarchical Auction Framework (MOHAF) for IoT resource allocation.
Author-email: Kushagra Agrawal <kush4409@gmail.com>, Polat Goktas <polat.goktas@gmail.com>
Project-URL: Homepage, https://github.com/afrilab/MOHAF-Resource-Allocation/
Project-URL: Bug Tracker, https://github.com/afrilab/MOHAF-Resource-Allocation/issues
Classifier: Development Status :: 3 - Alpha
Classifier: Intended Audience :: Science/Research
Classifier: License :: OSI Approved :: MIT License
Classifier: Programming Language :: Python :: 3
Classifier: Programming Language :: Python :: 3.8
Classifier: Programming Language :: Python :: 3.9
Classifier: Programming Language :: Python :: 3.10
Classifier: Operating System :: OS Independent
Classifier: Topic :: Scientific/Engineering :: Artificial Intelligence
Requires-Python: >=3.8
License-File: LICENSE
Requires-Dist: numpy
Requires-Dist: pandas
Requires-Dist: scikit-learn
Requires-Dist: matplotlib
Requires-Dist: seaborn
Requires-Dist: networkx
Requires-Dist: scipy
Dynamic: license-file
